odoo/addons/helpdesk_mgmt_rating/README.rst
odoo/addons/helpdesk_mgmt_rating/__init__.py
odoo/addons/helpdesk_mgmt_rating/__manifest__.py
odoo/addons/helpdesk_mgmt_rating/data/helpdesk_data.xml
odoo/addons/helpdesk_mgmt_rating/i18n/es.po
odoo/addons/helpdesk_mgmt_rating/i18n/es_AR.po
odoo/addons/helpdesk_mgmt_rating/i18n/helpdesk_mgmt_rating.pot
odoo/addons/helpdesk_mgmt_rating/models/__init__.py
odoo/addons/helpdesk_mgmt_rating/models/helpdesk_ticket.py
odoo/addons/helpdesk_mgmt_rating/models/helpdesk_ticket_stage.py
odoo/addons/helpdesk_mgmt_rating/readme/CONFIGURE.rst
odoo/addons/helpdesk_mgmt_rating/readme/CONTRIBUTORS.rst
odoo/addons/helpdesk_mgmt_rating/readme/DESCRIPTION.rst
odoo/addons/helpdesk_mgmt_rating/static/description/icon.png
odoo/addons/helpdesk_mgmt_rating/static/description/index.html
odoo/addons/helpdesk_mgmt_rating/views/helpdesk_ticket_menu.xml
odoo/addons/helpdesk_mgmt_rating/views/helpdesk_ticket_stage_views.xml
odoo/addons/helpdesk_mgmt_rating/views/helpdesk_ticket_views.xml
odoo13_addon_helpdesk_mgmt_rating-13.0.1.4.0.dist-info/METADATA
odoo13_addon_helpdesk_mgmt_rating-13.0.1.4.0.dist-info/WHEEL
odoo13_addon_helpdesk_mgmt_rating-13.0.1.4.0.dist-info/top_level.txt
odoo13_addon_helpdesk_mgmt_rating-13.0.1.4.0.dist-info/RECORD
